<?xml version="1.0" encoding="UTF-8"?>
<!DOCTYPE mapper PUBLIC "-//mybatis.org//DTD Mapper 3.0//EN" "http://mybatis.org/dtd/mybatis-3-mapper.dtd">
<mapper namespace="com.xinbao.mmbiz.sys.dao.SysUserOrganMapper">
  <resultMap id="BaseResultMap" type="com.xinbao.mmbiz.sys.entity.SysUserOrgan">
    <!--
      WARNING - @mbg.generated
      This element is automatically generated by MyBatis Generator, do not modify.
    -->
    <id column="ID" jdbcType="CHAR" property="id" />
    <result column="USER_ID" jdbcType="CHAR" property="userId" />
    <result column="ORGAN_ID" jdbcType="CHAR" property="organId" />
    <result column="CREATE_USER" jdbcType="VARCHAR" property="createUser" />
    <result column="CREATE_DATETIME" jdbcType="TIMESTAMP" property="createDatetime" />
    <result column="UPDATE_USER" jdbcType="VARCHAR" property="updateUser" />
    <result column="UPDATE_DATETIME" jdbcType="TIMESTAMP" property="updateDatetime" />
    <result column="REMARK" jdbcType="LONGVARCHAR" property="remark" />
  </resultMap>
  <delete id="deleteByPrimaryKey" parameterType="java.lang.String">
    <!--
      WARNING - @mbg.generated
      This element is automatically generated by MyBatis Generator, do not modify.
    -->
    delete from sys_user_organ
    where ID = #{id,jdbcType=CHAR}
  </delete>
  <insert id="insert" parameterType="com.xinbao.mmbiz.sys.entity.SysUserOrgan">
    <!--
      WARNING - @mbg.generated
      This element is automatically generated by MyBatis Generator, do not modify.
    -->
    insert into sys_user_organ (ID, USER_ID, ORGAN_ID, CREATE_USER, 
      CREATE_DATETIME, UPDATE_USER, UPDATE_DATETIME, 
      REMARK)
    values (#{id,jdbcType=CHAR}, #{userId,jdbcType=CHAR}, #{organId,jdbcType=CHAR}, #{createUser,jdbcType=VARCHAR}, 
      #{createDatetime,jdbcType=TIMESTAMP}, #{updateUser,jdbcType=VARCHAR}, #{updateDatetime,jdbcType=TIMESTAMP}, 
      #{remark,jdbcType=LONGVARCHAR})
  </insert>
  <update id="updateByPrimaryKey" parameterType="com.xinbao.mmbiz.sys.entity.SysUserOrgan">
    <!--
      WARNING - @mbg.generated
      This element is automatically generated by MyBatis Generator, do not modify.
    -->
    update sys_user_organ
    set USER_ID = #{userId,jdbcType=CHAR},
      ORGAN_ID = #{organId,jdbcType=CHAR},
      CREATE_USER = #{createUser,jdbcType=VARCHAR},
      CREATE_DATETIME = #{createDatetime,jdbcType=TIMESTAMP},
      UPDATE_USER = #{updateUser,jdbcType=VARCHAR},
      UPDATE_DATETIME = #{updateDatetime,jdbcType=TIMESTAMP},
      REMARK = #{remark,jdbcType=LONGVARCHAR}
    where ID = #{id,jdbcType=CHAR}
  </update>
  <select id="selectByPrimaryKey" parameterType="java.lang.String" resultMap="BaseResultMap">
    <!--
      WARNING - @mbg.generated
      This element is automatically generated by MyBatis Generator, do not modify.
    -->
    select ID, USER_ID, ORGAN_ID, CREATE_USER, CREATE_DATETIME, UPDATE_USER, UPDATE_DATETIME, 
    REMARK
    from sys_user_organ
    where ID = #{id,jdbcType=CHAR}
  </select>
  <select id="selectAll" resultMap="BaseResultMap">
    <!--
      WARNING - @mbg.generated
      This element is automatically generated by MyBatis Generator, do not modify.
    -->
    select ID, USER_ID, ORGAN_ID, CREATE_USER, CREATE_DATETIME, UPDATE_USER, UPDATE_DATETIME, 
    REMARK
    from sys_user_organ
  </select>
</mapper>